odoo10_addon_l10n_eu_nace-10.0.1.0.0.99.dev3-py2.7-nspkg.pth
odoo/addons/l10n_eu_nace/README.rst
odoo/addons/l10n_eu_nace/__init__.py
odoo/addons/l10n_eu_nace/__manifest__.py
odoo/addons/l10n_eu_nace/data/NACE_REV2_bg.csv
odoo/addons/l10n_eu_nace/data/NACE_REV2_cs.csv
odoo/addons/l10n_eu_nace/data/NACE_REV2_da.csv
odoo/addons/l10n_eu_nace/data/NACE_REV2_de.csv
odoo/addons/l10n_eu_nace/data/NACE_REV2_el.csv
odoo/addons/l10n_eu_nace/data/NACE_REV2_en.csv
odoo/addons/l10n_eu_nace/data/NACE_REV2_es.csv
odoo/addons/l10n_eu_nace/data/NACE_REV2_et.csv
odoo/addons/l10n_eu_nace/data/NACE_REV2_fi.csv
odoo/addons/l10n_eu_nace/data/NACE_REV2_fr.csv
odoo/addons/l10n_eu_nace/data/NACE_REV2_hr.csv
odoo/addons/l10n_eu_nace/data/NACE_REV2_hu.csv
odoo/addons/l10n_eu_nace/data/NACE_REV2_it.csv
odoo/addons/l10n_eu_nace/data/NACE_REV2_lt.csv
odoo/addons/l10n_eu_nace/data/NACE_REV2_lv.csv
odoo/addons/l10n_eu_nace/data/NACE_REV2_mt.csv
odoo/addons/l10n_eu_nace/data/NACE_REV2_nl.csv
odoo/addons/l10n_eu_nace/data/NACE_REV2_no.csv
odoo/addons/l10n_eu_nace/data/NACE_REV2_pl.csv
odoo/addons/l10n_eu_nace/data/NACE_REV2_pt.csv
odoo/addons/l10n_eu_nace/data/NACE_REV2_ro.csv
odoo/addons/l10n_eu_nace/data/NACE_REV2_ru.csv
odoo/addons/l10n_eu_nace/data/NACE_REV2_sk.csv
odoo/addons/l10n_eu_nace/data/NACE_REV2_sl.csv
odoo/addons/l10n_eu_nace/data/NACE_REV2_sv.csv
odoo/addons/l10n_eu_nace/data/NACE_REV2_tr.csv
odoo/addons/l10n_eu_nace/data/make_data.py
odoo/addons/l10n_eu_nace/data/res.partner.category.csv
odoo/addons/l10n_eu_nace/i18n/bg.po
odoo/addons/l10n_eu_nace/i18n/cs.po
odoo/addons/l10n_eu_nace/i18n/da.po
odoo/addons/l10n_eu_nace/i18n/de.po
odoo/addons/l10n_eu_nace/i18n/el.po
odoo/addons/l10n_eu_nace/i18n/es.po
odoo/addons/l10n_eu_nace/i18n/et.po
odoo/addons/l10n_eu_nace/i18n/fi.po
odoo/addons/l10n_eu_nace/i18n/fr.po
odoo/addons/l10n_eu_nace/i18n/hr.po
odoo/addons/l10n_eu_nace/i18n/hu.po
odoo/addons/l10n_eu_nace/i18n/it.po
odoo10_addon_l10n_eu_nace-10.0.1.0.0.99.dev3.dist-info/METADATA
odoo10_addon_l10n_eu_nace-10.0.1.0.0.99.dev3.dist-info/RECORD
odoo10_addon_l10n_eu_nace-10.0.1.0.0.99.dev3.dist-info/WHEEL
odoo10_addon_l10n_eu_nace-10.0.1.0.0.99.dev3.dist-info/namespace_packages.txt
odoo10_addon_l10n_eu_nace-10.0.1.0.0.99.dev3.dist-info/top_level.txt
